xbox/webapi/api/__init__.py
xbox/webapi/api/client.py
xbox/webapi/api/language.py
xbox/webapi/api/provider/__init__.py
xbox/webapi/api/provider/baseprovider.py
xbox/webapi/api/provider/account/__init__.py
xbox/webapi/api/provider/account/models.py
xbox/webapi/api/provider/achievements/__init__.py
xbox/webapi/api/provider/achievements/models.py
xbox/webapi/api/provider/catalog/__init__.py
xbox/webapi/api/provider/catalog/const.py
xbox/webapi/api/provider/catalog/models.py
xbox/webapi/api/provider/cqs/__init__.py
xbox/webapi/api/provider/cqs/models.py
xbox/webapi/api/provider/gameclips/__init__.py
xbox/webapi/api/provider/gameclips/models.py
xbox/webapi/api/provider/lists/__init__.py
xbox/webapi/api/provider/lists/models.py
xbox/webapi/api/provider/mediahub/__init__.py
xbox/webapi/api/provider/mediahub/models.py
xbox/webapi/api/provider/message/__init__.py
xbox/webapi/api/provider/message/models.py
xbox/webapi/api/provider/people/__init__.py
xbox/webapi/api/provider/people/models.py
xbox/webapi/api/provider/presence/__init__.py
xbox/webapi/api/provider/presence/models.py
xbox/webapi/api/provider/profile/__init__.py
xbox/webapi/api/provider/profile/models.py
xbox/webapi/api/provider/screenshots/__init__.py
xbox/webapi/api/provider/screenshots/models.py
xbox/webapi/api/provider/smartglass/__init__.py
xbox/webapi/api/provider/smartglass/models.py
xbox/webapi/api/provider/titlehub/__init__.py
xbox/webapi/api/provider/titlehub/models.py
xbox/webapi/api/provider/usersearch/__init__.py
xbox/webapi/api/provider/usersearch/models.py
xbox/webapi/api/provider/userstats/__init__.py
xbox/webapi/api/provider/userstats/models.py
xbox/webapi/authentication/__init__.py
xbox/webapi/authentication/manager.py
xbox/webapi/authentication/models.py
xbox/webapi/authentication/xal.py
xbox/webapi/common/__init__.py
xbox/webapi/common/exceptions.py
xbox/webapi/common/filetimes.py
xbox/webapi/common/models.py
xbox/webapi/common/request_signer.py
xbox/webapi/common/signed_session.py
xbox_webapi-2.1.0.dist-info/LICENSE
xbox_webapi-2.1.0.dist-info/METADATA
xbox_webapi-2.1.0.dist-info/WHEEL
xbox_webapi-2.1.0.dist-info/entry_points.txt
xbox_webapi-2.1.0.dist-info/top_level.txt
xbox_webapi-2.1.0.dist-info/RECORD
