Metadata-Version: 2.1
Name: xbox-webapi
Version: 2.1.0
Summary: A library to authenticate with Windows Live/Xbox Live and use their API
Author: OpenXbox
License: GPL
Project-URL: Homepage, https://github.com/OpenXbox/xbox-webapi-python
Keywords: xbox one live api
Classifier: Development Status :: 4 - Beta
Classifier: Intended Audience :: Developers
Classifier: License :: OSI Approved :: MIT License
Classifier: Programming Language :: Python :: 3
Classifier: Programming Language :: Python :: 3.8
Classifier: Programming Language :: Python :: 3.9
Classifier: Programming Language :: Python :: 3.10
Classifier: Programming Language :: Python :: 3.11
Classifier: Programming Language :: Python :: 3.12
Classifier: Topic :: Software Development :: Libraries :: Python Modules
Requires-Python: >=3.8
License-File: LICENSE
Requires-Dist: appdirs
Requires-Dist: ecdsa
Requires-Dist: httpx
Requires-Dist: ms-cv
Requires-Dist: pydantic ==2.*
Provides-Extra: dev
Requires-Dist: bump2version ; extra == 'dev'
Requires-Dist: coverage ; extra == 'dev'
Requires-Dist: pytest ; extra == 'dev'
Requires-Dist: pytest-asyncio ; extra == 'dev'
Requires-Dist: pytest-cov ; extra == 'dev'
Requires-Dist: pytest-runner ; extra == 'dev'
Requires-Dist: respx ; extra == 'dev'
Requires-Dist: twine ; extra == 'dev'
Requires-Dist: watchdog ; extra == 'dev'
Requires-Dist: wheel ; extra == 'dev'
Requires-Dist: ruff ==0.1.6 ; extra == 'dev'
Requires-Dist: pre-commit ==3.5.0 ; extra == 'dev'
Requires-Dist: pyupgrade ==3.15.0 ; extra == 'dev'
Requires-Dist: black ==23.11.0 ; extra == 'dev'
Requires-Dist: pydocstyle ==6.1.1 ; extra == 'dev'
Requires-Dist: bandit ==1.7.5 ; extra == 'dev'
Requires-Dist: isort ==5.12.0 ; extra == 'dev'
Provides-Extra: docs
Requires-Dist: Sphinx ; extra == 'docs'
Requires-Dist: sphinx-mdinclude ; extra == 'docs'
Requires-Dist: sphinx-rtd-theme ; extra == 'docs'
